dds/__init__.py
dds/_annotations.py
dds/_api.py
dds/_config.py
dds/_eval_ctx.py
dds/_global_ctx.py
dds/_introspect_indirect.py
dds/_lambda_funs.py
dds/_lru_store.py
dds/_plotting.py
dds/_print_ast.py
dds/_retrieve_objects.py
dds/_version.py
dds/codec.py
dds/fun_args.py
dds/introspect.py
dds/py.typed
dds/store.py
dds/structures.py
dds/structures_utils.py
dds/codecs/__init__.py
dds/codecs/builtins.py
dds/codecs/databricks.py
dds/codecs/pandas.py
dds_py-0.13.1.dist-info/LICENSE
dds_py-0.13.1.dist-info/METADATA
dds_py-0.13.1.dist-info/WHEEL
dds_py-0.13.1.dist-info/top_level.txt
dds_py-0.13.1.dist-info/RECORD
