Metadata-Version: 2.1
Name: dds-py
Version: 0.13.1
Summary: PyDDS: data-driven programing
Home-page: https://github.com/tjhunter/dds_py
Author: Tim Hunter
Author-email: tjhunter+dds@cs.stanford.edu
License: AGPL
Project-URL: Bug Tracker, https://github.com/tjhunter/dds_py/issues
Project-URL: Documentation, https://tjhunter.github.io/dds_py/
Project-URL: Source Code, https://github.com/tjhunter/dds_py
Classifier: License :: OSI Approved :: GNU Affero General Public License v3 or later (AGPLv3+)
Classifier: Intended Audience :: Developers
Classifier: Topic :: Software Development :: Libraries :: Application Frameworks
Classifier: Typing :: Typed
Classifier: Development Status :: 4 - Beta
Classifier: Programming Language :: Python :: 3 :: Only
Classifier: Programming Language :: Python :: 3.8
Classifier: Programming Language :: Python :: 3.9
Classifier: Programming Language :: Python :: 3.10
Classifier: Programming Language :: Python :: 3.11
Requires-Python: >=3.6,<4
License-File: LICENSE
Requires-Dist: asttokens
Provides-Extra: pandas
Requires-Dist: pandas >=0.23.1 ; extra == 'pandas'
Requires-Dist: pyarrow >=0.10 ; extra == 'pandas'
Provides-Extra: spark
Requires-Dist: pyspark >=2.4.0 ; extra == 'spark'
